molang/__init__.py
molang/core.py
molang/helper.py
molang/models.py
molang_chain-0.1.4.dist-info/METADATA
molang_chain-0.1.4.dist-info/WHEEL
molang_chain-0.1.4.dist-info/top_level.txt
molang_chain-0.1.4.dist-info/RECORD
